.gitignore
MANIFEST.in
README.txt
bootstrap.py
buildout40.cfg
buildout41.cfg
buildout42.cfg
buildout43.cfg
setup.py
sources.cfg
collective/__init__.py
collective.blog.star.egg-info/PKG-INFO
collective.blog.star.egg-info/SOURCES.txt
collective.blog.star.egg-info/dependency_links.txt
collective.blog.star.egg-info/entry_points.txt
collective.blog.star.egg-info/namespace_packages.txt
collective.blog.star.egg-info/not-zip-safe
collective.blog.star.egg-info/requires.txt
collective.blog.star.egg-info/top_level.txt
collective/blog/__init__.py
collective/blog/star/__init__.py
collective/blog/star/configure.zcml
collective/blog/star/profile.py
collective/blog/star/rebuild_i18n.sh
collective/blog/star/version.txt
collective/blog/star/locales/collective.blog.star.pot
collective/blog/star/locales/en/LC_MESSAGES/collective.blog.star.po
collective/blog/star/locales/es/LC_MESSAGES/collective.blog.star.po
collective/blog/star/profiles/default/metadata.xml
docs/HISTORY.txt
docs/INSTALL.txt
docs/LICENSE.GPL
docs/LICENSE.txt
products/README.txt
var/README.txt