Metadata-Version: 1.1
Name: collective.blog.star
Version: 1.2.1
Summary: Blog suite for Plone
Home-page: https://github.com/collective/collective.blog.star
Author: Jarn AS
Author-email: info@jarn.com
License: GPL
Keywords: plone blog
Platform: UNKNOWN
Classifier: Framework :: Plone
Classifier: Framework :: Plone :: 4.0
Classifier: Framework :: Plone :: 4.1
Classifier: Framework :: Plone :: 4.2
Classifier: Framework :: Plone :: 4.3
Classifier: Programming Language :: Python
Classifier: Programming Language :: Python :: 2.6
Classifier: Programming Language :: Python :: 2.7
